codigo/__init__.py
codigo/comando.py
devopstrabalhofinal-0.0.7.dist-info/LICENSE
devopstrabalhofinal-0.0.7.dist-info/METADATA
devopstrabalhofinal-0.0.7.dist-info/WHEEL
devopstrabalhofinal-0.0.7.dist-info/top_level.txt
devopstrabalhofinal-0.0.7.dist-info/RECORD
